json_to_ndjsonify/__init__.py
json_to_ndjsonify/main.py
tests/__init__.py
tests/test_main.py
json_to_ndjsonify-0.1.0.dist-info/LICENSE.md
json_to_ndjsonify-0.1.0.dist-info/METADATA
json_to_ndjsonify-0.1.0.dist-info/WHEEL
json_to_ndjsonify-0.1.0.dist-info/entry_points.txt
json_to_ndjsonify-0.1.0.dist-info/top_level.txt
json_to_ndjsonify-0.1.0.dist-info/RECORD
