Metadata-Version: 2.1
Name: json-to-ndjsonify
Version: 0.1.0
Summary: A small package to convert JSON files to NDJSON (Newline Delimited JSON) format.
Home-page: https://github.com/mohjak/json-to-ndjsonify
Author: Mohammad Jaqmaqji
Author-email: mohjak@gmail.com
Classifier: Programming Language :: Python :: 3
Classifier: License :: OSI Approved :: MIT License
Classifier: Operating System :: OS Independent
License-File: LICENSE.md
